[
  {
    "id": "b1000000-0000-0000-0000-000000000001",
    "booking_ref": "AC-2024-0001",
    "customer_name": "Mohammed Al-Rashidi",
    "customer_phone": "+966501234567",
    "customer_email": "m.rashidi@gmail.com",
    "pickup_location": "King Khalid International Airport, Riyadh",
    "dropoff_location": "Al Olaya District, Riyadh",
    "pickup_date": "2024-04-30",
    "pickup_time": "14:30",
    "service_type": "airport",
    "passengers": 2,
    "payment_method": "cash",
    "payment_status": "pending",
    "booking_status": "confirmed",
    "price_estimate": 120,
    "final_price": null,
    "notes": "Flight SV302 from London. Has 3 luggage bags.",
    "admin_notes": "Driver Ibrahim confirmed. Meeting at arrivals gate.",
    "created_at": "2024-04-29T10:15:00Z",
    "updated_at": "2024-04-29T11:00:00Z"
  },
  {
    "id": "b2000000-0000-0000-0000-000000000002",
    "booking_ref": "AC-2024-0002",
    "customer_name": "Fatima Al-Zahrani",
    "customer_phone": "+966557891234",
    "customer_email": "fatima.z@hotmail.com",
    "pickup_location": "Riyadh Park Mall, Riyadh",
    "dropoff_location": "King Abdullah Financial District (KAFD), Riyadh",
    "pickup_date": "2024-04-30",
    "pickup_time": "09:00",
    "service_type": "standard",
    "passengers": 1,
    "payment_method": "online",
    "payment_status": "paid",
    "booking_status": "completed",
    "price_estimate": 45,
    "final_price": 45,
    "notes": "",
    "admin_notes": "",
    "created_at": "2024-04-29T20:00:00Z",
    "updated_at": "2024-04-30T09:45:00Z"
  },
  {
    "id": "b3000000-0000-0000-0000-000000000003",
    "booking_ref": "AC-2024-0003",
    "customer_name": "Abdullah Al-Ghamdi",
    "customer_phone": "+966509876543",
    "customer_email": null,
    "pickup_location": "Jeddah Corniche, Jeddah",
    "dropoff_location": "King Abdulaziz International Airport, Jeddah",
    "pickup_date": "2024-05-01",
    "pickup_time": "06:00",
    "service_type": "airport",
    "passengers": 3,
    "payment_method": "cash",
    "payment_status": "pending",
    "booking_status": "pending",
    "price_estimate": 95,
    "final_price": null,
    "notes": "Early morning flight. Please arrive 15 minutes early.",
    "admin_notes": "",
    "created_at": "2024-04-30T14:20:00Z",
    "updated_at": "2024-04-30T14:20:00Z"
  },
  {
    "id": "b4000000-0000-0000-0000-000000000004",
    "booking_ref": "AC-2024-0004",
    "customer_name": "Omar Al-Dossari",
    "customer_phone": "+966543219876",
    "customer_email": "omar.dossari@company.sa",
    "pickup_location": "Dammam City Center Mall",
    "dropoff_location": "Riyadh City, Al Malaz District",
    "pickup_date": "2024-05-02",
    "pickup_time": "11:00",
    "service_type": "standard",
    "passengers": 1,
    "payment_method": "online",
    "payment_status": "paid",
    "booking_status": "in_progress",
    "price_estimate": 380,
    "final_price": null,
    "notes": "Business trip. Need quiet ride.",
    "admin_notes": "VIP customer. Provide luxury vehicle.",
    "created_at": "2024-04-30T08:00:00Z",
    "updated_at": "2024-05-02T11:10:00Z"
  },
  {
    "id": "b5000000-0000-0000-0000-000000000005",
    "booking_ref": "AC-2024-0005",
    "customer_name": "Nora Al-Mutairi",
    "customer_phone": "+966512345678",
    "customer_email": "nora.m@gmail.com",
    "pickup_location": "Makkah Al-Mukarramah, near Haram",
    "dropoff_location": "Madinah Al-Munawwarah, near Masjid Nabawi",
    "pickup_date": "2024-05-03",
    "pickup_time": "08:00",
    "service_type": "tour",
    "passengers": 4,
    "payment_method": "cash",
    "payment_status": "pending",
    "booking_status": "pending",
    "price_estimate": 450,
    "final_price": null,
    "notes": "Family trip for Umrah. Need family-sized vehicle.",
    "admin_notes": "",
    "created_at": "2024-04-30T16:45:00Z",
    "updated_at": "2024-04-30T16:45:00Z"
  }
]
